CHANGELOG.rst
MANIFEST.in
README.rst
setup.cfg
setup.py
./DeepJetCore/bin/addPredictionLabels.py
./DeepJetCore/bin/batch_conversion.py
./DeepJetCore/bin/check_conversion.py
./DeepJetCore/bin/convertDCtoNumpy.py
./DeepJetCore/bin/convertFromRoot.py
./DeepJetCore/bin/convertToTF.py
./DeepJetCore/bin/plotLoss.py
./DeepJetCore/bin/predict.py
DeepJetCore/DataCollection.py
DeepJetCore/MultiDataCollection.py
DeepJetCore/TrainData.py
DeepJetCore/Weighter.py
DeepJetCore/__init__.py
DeepJetCore/gpu_env.sh
DeepJetCore/lxplus_env.sh
DeepJetCore/modeltools.py
DeepJetCore/new_env.sh
DeepJetCore/stopwatch.py
DeepJetCore.egg-info/PKG-INFO
DeepJetCore.egg-info/SOURCES.txt
DeepJetCore.egg-info/dependency_links.txt
DeepJetCore.egg-info/not-zip-safe
DeepJetCore.egg-info/requires.txt
DeepJetCore.egg-info/top_level.txt
DeepJetCore/bin/__init__.py
DeepJetCore/bin/addPredictionLabels.py
DeepJetCore/bin/batch_conversion.py
DeepJetCore/bin/check_conversion.py
DeepJetCore/bin/convertDCtoNumpy.py
DeepJetCore/bin/convertFromRoot.py
DeepJetCore/bin/convertToTF.py
DeepJetCore/bin/plotLoss.py
DeepJetCore/bin/predict.py
DeepJetCore/compiled/.gitignore
DeepJetCore/compiled/Makefile
DeepJetCore/compiled/Makefile.djl3.bak
DeepJetCore/compiled/README
DeepJetCore/compiled/__init__.py
DeepJetCore/compiled/c_makePlots.o
DeepJetCore/compiled/c_makePlots.so
DeepJetCore/compiled/c_makeROCs.o
DeepJetCore/compiled/c_makeROCs.so
DeepJetCore/compiled/c_meanNormZeroPad.o
DeepJetCore/compiled/c_meanNormZeroPad.so
DeepJetCore/compiled/c_randomSelect.o
DeepJetCore/compiled/c_randomSelect.so
DeepJetCore/compiled/c_readArrThreaded.o
DeepJetCore/compiled/c_readArrThreaded.so
DeepJetCore/compiled/c_storeTensor.o
DeepJetCore/compiled/c_storeTensor.so
DeepJetCore/compiled/friendTreeInjector.so
DeepJetCore/compiled/helper.so
DeepJetCore/compiled/indata.so
DeepJetCore/compiled/libquicklz.so
DeepJetCore/compiled/quicklzpy.c
DeepJetCore/compiled/rocCurve.so
DeepJetCore/compiled/rocCurveCollection.so
DeepJetCore/compiled/cpp/friendTreeInjector.cpp
DeepJetCore/compiled/cpp/friendTreeInjector.i
DeepJetCore/compiled/cpp/friendTreeInjector.py
DeepJetCore/compiled/cpp/friendTreeInjector_wrap.cxx
DeepJetCore/compiled/cpp/helper.cpp
