Metadata-Version: 1.2
Name: DeepJetCore
Version: 1.0.0
Summary: The DeepJetCore Library: Deep Learning       for High-energy Physics
Home-page: https://github.com/DL4J/DeepJetCore
Author: CERN - CMS Group (EP-CMG-PS)
Author-email: swapneel.mehta@cern.ch
License: Apache
Project-URL: Source, https://github.com/SwapneelM/DeepJetCore
Project-URL: Documentation, https://github.com/SwapneelM/DeepJetCore/wiki
Keywords: deep-learning physics jets cern cms
Platform: UNKNOWN
Classifier: Development Status :: 3 - Alpha
Classifier: License :: OSI Approved :: Apache Software License
Classifier: Intended Audience :: Developers
Classifier: Intended Audience :: Science/Research
Classifier: Operating System :: Unix
Classifier: Programming Language :: Python :: 2.7
Requires-Python: ~=2.7
